AmiAutomation/LogData.py
AmiAutomation/PX3_Bin.py
AmiAutomation/RphData.py
AmiAutomation/__init__.py
AmiAutomation-0.1.5.6.data/data/DLLs/DigitArcPX3.Tools.DataToPython.dll
AmiAutomation-0.1.5.6.data/data/DLLs/ICSharpCode.SharpZipLib.dll
AmiAutomation-0.1.5.6.data/data/DLLs/Kernel.Message.dll
AmiAutomation-0.1.5.6.dist-info/LICENSE
AmiAutomation-0.1.5.6.dist-info/METADATA
AmiAutomation-0.1.5.6.dist-info/WHEEL
AmiAutomation-0.1.5.6.dist-info/top_level.txt
AmiAutomation-0.1.5.6.dist-info/RECORD
