Metadata-Version: 2.1
Name: AmiAutomation
Version: 0.1.5.6
Summary: Package to extract binary files into pandas dataframes
Home-page: UNKNOWN
Author: AMI
Author-email: luis.castro@amiautomation.com
License: UNKNOWN
Platform: UNKNOWN
Classifier: Programming Language :: Python :: 3
Classifier: License :: OSI Approved :: MIT License
Classifier: Operating System :: Microsoft :: Windows :: Windows 10
Requires-Python: >=3.6
Requires-Dist: pandas (>=1.1.0)
